argo_workflow_tools_visualization/__init__.py
argo_workflow_tools_visualization/dsl/__init__.py
argo_workflow_tools_visualization/dsl/dependencies_graph/__init__.py
argo_workflow_tools_visualization/dsl/dependencies_graph/build_workflow_dependencies_graph.py
argo_workflow_tools_visualization/dsl/dependencies_graph/plot_workflow_dependencies_graph.py
argo_workflow_tools_visualization-0.1.3.dist-info/WHEEL
argo_workflow_tools_visualization-0.1.3.dist-info/METADATA
argo_workflow_tools_visualization-0.1.3.dist-info/RECORD
