Metadata-Version: 2.1
Name: argo-workflow-tools-visualization
Version: 0.1.3
Summary: Visualization tools for the argo-workflow-tools package
Home-page: https://github.com/DiagnosticRobotics/argo-workflow-tools
License: Apache 2.0
Author: Diagnostic Robotics
Requires-Python: >=3.7,<4.0
Classifier: License :: Other/Proprietary License
Classifier: Programming Language :: Python :: 3
Classifier: Programming Language :: Python :: 3.10
Classifier: Programming Language :: Python :: 3.7
Classifier: Programming Language :: Python :: 3.8
Classifier: Programming Language :: Python :: 3.9
Requires-Dist: argo-workflow-tools (>=0.9.45,<0.10.0)
Requires-Dist: graphviz (>=0.19.1,<0.20.0)
Requires-Dist: networkx (>=2.6.3,<3.0.0)
Requires-Dist: pydot (>=1.4.2,<2.0.0)
Project-URL: Repository, https://github.com/DiagnosticRobotics/argo-workflow-tools
